Lab3/cpu/cpu.v
module cpu (PC, INSTRUCTION, CLK, RESET);
/*
=============================================
            Port Declarations
=============================================
*/
    input               CLK, RESET;         // For PC and the reg_file
    input       [31:0]  INSTRUCTION;

    // adder ports
    output  reg [7:0]  PC;
    wire        [7:0]  next_pc;

    // control_unit ports
    wire        [7:0]   op_code;

    //reg_file ports
    wire                write_enable;
    wire        [2:0]   write_reg;
    wire        [2:0]   read_reg_1;
    wire        [2:0]   read_reg_2;

    wire        [7:0]   write_val;          // Output of the ALU
    

    // twos_complement ports
    wire        [7:0]   in_val;

    // mux1 ports
    wire        [7:0]   regout2;
    wire        [7:0]   twos_comp_res;
    wire                reg2_or_twos_comp;


    // mux2 ports
    wire        [7:0]   mux1_res;
    wire        [7:0]   immediate;
    wire                reg_or_imm;


    // ALU ports
    wire        [7:0]   alu_op_1;
    wire        [7:0]   alu_op_2;
    wire        [2:0]   select;

/*
=============================================
            Instruction Memory      
=============================================
*/

    // // 32-bits wide 64 instructions (256 bytes)
    // reg [31:0] instruction_memory [0:64];


/*
=============================================
        External Module Instantiation      
=============================================
*/

    adder my_adder(
        .PC_IN(PC),
        .PC_OUT(next_pc)
    );

    twos_complement my_twos_complement(
        .IN_VAL(in_val),
        .OUT_VAL(twos_comp_res)
    );

    control_unit my_control_unit(
        .OP_CODE(op_code),
        .WRITE_ENABLE(write_enable),
        .ORIG_OR_TWOS_COMP(reg2_or_twos_comp),
        .REG_OR_IMM(reg_or_imm),
        .ALU_OP(select)
    );

    alu my_alu(
        .DATA1(alu_op_1),
        .DATA2(alu_op_2),
        .SELECT(select),
        .RESULT(write_val)

    );

    reg_file my_reg_file (
        .IN(write_val),
        .INADDRESS(write_reg),
        .OUT1ADDRESS(read_reg_1),
        .OUT2ADDRESS(read_reg_2),
        .OUT1(alu_op_1),
        .OUT2(regout2),
        .WRITE(write_enable),
        .CLK(CLK),
        .RESET(RESET)
    );

    mux_2to1 my_mux_1 (
        .INPUT1(regout2),
        .INPUT2(twos_comp_res),
        .SELECT(reg2_or_twos_comp),
        .OUT_VAL(mux1_res)
    );

    mux_2to1 my_mux_2 (
        .INPUT1(mux1_res),
        .INPUT2(immediate),
        .SELECT(reg_or_imm),
        .OUT_VAL(alu_op_2)
    );


/*
=============================================
        Decoding an instruction      
=============================================
*/

    // derive immediate and twos-complement input
    assign in_val = regout2;
    assign immediate = INSTRUCTION[7:0];

    assign op_code    = INSTRUCTION[31:24];
    assign write_reg  = INSTRUCTION[18:16];
    assign read_reg_1 = INSTRUCTION[10:8];
    assign read_reg_2 = INSTRUCTION[2:0];



    always @(posedge CLK) begin
        if (RESET == 1) begin
            #1 PC = 0;
        end
        else begin
            #1 PC = next_pc;
        end
    end

endmodule


module adder (
    input   [7:0]  PC_IN,
    output  [7:0]  PC_OUT
);
    
    assign #1 PC_OUT = PC_IN + 8'd4;
    
endmodule



module control_unit(
    
    input       [7:0]   OP_CODE,

    output reg          WRITE_ENABLE, ORIG_OR_TWOS_COMP, REG_OR_IMM,
    output reg  [2:0]   ALU_OP

);

    always @(*) begin
        
        #1;

        ORIG_OR_TWOS_COMP = 1'b0;
        REG_OR_IMM = 1'b0;
        WRITE_ENABLE = 1'b0;
        ALU_OP = 3'b000;


        case (OP_CODE)
            
            // ADD reg_dest, reg_read1, reg_read2
            8'h00: begin
                
                WRITE_ENABLE = 1'b1;
                ALU_OP = 3'd1;

            end

            // SUB reg_dest, reg_read1, reg_read2
            8'h01: begin
                
                WRITE_ENABLE = 1'b1;
                ALU_OP = 3'd1;
                ORIG_OR_TWOS_COMP = 1'b1;      // TO choose the twos' complement value

            end
            
            // AND reg_dest, reg_read1, reg_read2
            8'h02: begin
                
                WRITE_ENABLE = 1'b1;
                ALU_OP = 3'd3;

            end

            // OR reg_dest, reg_read1, reg_read2
            8'h03: begin
                
                WRITE_ENABLE = 1'b1;
                ALU_OP = 3'd4;

            end

            // MOV reg_dest, reg_read1
            8'h06: begin
                
                WRITE_ENABLE = 1'b1;
                ALU_OP = 3'd0;
                REG_OR_IMM = 1'b0;

            end
            
            // LOADI reg_dest, imm
            8'h07: begin
                
                WRITE_ENABLE = 1'b1;
                ALU_OP = 3'd0;
                REG_OR_IMM = 1'b1;         

            end

            default: begin
                WRITE_ENABLE = 1'b0;
            end

        endcase

    end

endmodule



/*
=============================================
                2-to-1 MUX      
=============================================
*/

module mux_2to1(
    input [7:0] INPUT1, INPUT2,
    input SELECT,
    output reg [7:0] OUT_VAL
);

    always @(*) begin
        case (SELECT)
            0: begin
                OUT_VAL = INPUT1;
            end

            1: begin
                OUT_VAL = INPUT2;
            
            end
            default: begin
                OUT_VAL = INPUT1;
            end 
        endcase
    end

endmodule



module twos_complement(
    input [7:0] IN_VAL,
    output [7:0] OUT_VAL
);

    assign OUT_VAL = (~IN_VAL) + 1;

endmodule


/*
=========================================================================
                            A      L       U     U
                           A A     L       U     U
                          AAAAA    L       U     U
                         A     A   L       U     U
                        A       A  LLLLLL    UUU
=========================================================================
*/

module alu(DATA1, DATA2, SELECT, RESULT);

                                                /*
    ============================================
                Port Declarations
    ============================================*/

    // 8-bit Data inputs
    input [7:0] DATA1, DATA2;
    
    // Selection input
    input [2:0] SELECT;

    // 8-bit output result
    output [7:0] RESULT;

    // 8-bit wires to hold the results of each operation
    wire [7:0] forward_result;
    wire [7:0] add_result;
    wire [7:0] and_result;
    wire [7:0] or_result;

                                                /*
    ============================================
                Module Instantiations
    ============================================*/
    
    // Forward module to forward DATA2 when SELECT is 000
    FORWARD myforward(
        .DATA2(DATA2), 
        .RESULT(forward_result)
    );

    // ADD module to add DATA1 and DATA2 when SELECT is 001
    ADD myadd(
        .DATA1(DATA1),
        .DATA2(DATA2),
        .RESULT(add_result)
    );
    
    // AND module to perform bitwise AND on DATA1 and DATA2 when SELECT is 010
    AND myand(
        .DATA1(DATA1),
        .DATA2(DATA2),
        .RESULT(and_result)
    );

    // OR module to perform bitwise OR on DATA1 and DATA2 when SELECT is 011
    OR myor(
        .DATA1(DATA1),
        .DATA2(DATA2),
        .RESULT(or_result)
    );

    // Continuous assignment to RESULT based on the value of SELECT
    assign RESULT = (SELECT == 3'b000) ? forward_result :
                    (SELECT == 3'b001) ? add_result :
                    (SELECT == 3'b010) ? and_result :
                    (SELECT == 3'b011) ? or_result :
                    8'b0;

endmodule


                                                /*
    ============================================
                Module Declarations
    ============================================*/

// Forward module to forward DATA2 when SELECT is 000
module FORWARD(DATA2, RESULT);

    input [7:0] DATA2;
    output reg [7:0] RESULT;
    
    always @ (DATA2)
    begin
        // Forwarding DATA2 to RESULT with a delay of 1 time unit
        #1 RESULT <= DATA2;
    end

endmodule



// ADD module to add DATA1 and DATA2 when SELECT is 001
module ADD(DATA1, DATA2, RESULT);

    input [7:0] DATA1, DATA2;
    output reg [7:0] RESULT;
    
    always @ (DATA1, DATA2)
    begin
        // Adding DATA1 and DATA2 and assigning the result to RESULT with a delay of 2 time units
        #2 RESULT <= DATA1 + DATA2;
    end

endmodule

// AND module to perform bitwise AND on DATA1 and DATA2 when SELECT is 010
module AND(DATA1, DATA2, RESULT);

    input [7:0] DATA1, DATA2;
    output reg [7:0] RESULT;
    
    always @ (DATA1, DATA2)
    begin
        // Performing bitwise AND on DATA1 and DATA2 and 
        // assigning the result to RESULT with a delay of 1 time unit
        #1 RESULT <= DATA1 & DATA2;
    end

endmodule


// OR module to perform bitwise OR on DATA1 and DATA2 when SELECT is 011
module OR(DATA1, DATA2, RESULT);

    input [7:0] DATA1, DATA2;
    output reg [7:0] RESULT;
    
    always @ (DATA1, DATA2)
    begin
        // Performing bitwise OR on DATA1 and DATA2 and
        // assigning the result to RESULT with a delay of 1 time unit  
        #1 RESULT <= DATA1 | DATA2;
    end

endmodule



/*
=========================================================================
        RRRRR   EEEEE    GGGG      FFFFF III  L       EEEEE
        R    R  E       G          F      I   L       E
        RRRR    EEEE   G   GG      FFFF   I   L       EEEE
        R   R   E       G   G      F      I   L       E
        R    R  EEEEE    GGGG      F     III  LLLLLL  EEEEE
=========================================================================
*/


module reg_file(IN, OUT1, OUT2, INADDRESS, OUT1ADDRESS, OUT2ADDRESS, WRITE, CLK, RESET);
    
                                                /*
    ============================================
                Port Declarations
    ============================================*/

    // Inputs
    
    // Input value to store  
    input [7:0] IN;   

    // Clock input, Write command, Reset commmand
    input CLK, WRITE, RESET;                            
    
    // Input register address to store
    // Output register adress 1 to output value 1
    // Output register adress 2 to output value 2
    input [2:0] INADDRESS, OUT1ADDRESS, OUT2ADDRESS;    
    
    // OUT1 and OUT2 is not declared as reg becuase continuous assignment doesn't allow that.
    // Therefore, they are kept as net values
    output wire [7:0] OUT1, OUT2;


                                                /*
    ============================================
          Internal Storage (8x8 register)
    ============================================*/

    // Declaring an array of 8, 8-byte arrays
    reg [7:0] reg_array [7:0];

    // Declaring integer i for the 'for' loop
    integer i;


                                                /*
    ============================================
            Reading Logic (Asynchronous)
    ============================================*/

    // Continuous assignment to OUT1 and OUT2
    // the values obtained from OUT1ADDRESS and OUT2ADDRESS
    assign #2 OUT1 = reg_array[OUT1ADDRESS];
    assign #2 OUT2 = reg_array[OUT2ADDRESS];


                                                /*
    ============================================
         Write and Reset Logic (Synchronous)
    ============================================*/

    // This 'always' block triggers when the clock is set to 1
    always @ (posedge CLK) begin
        
        // If reset input is 1, all of the registers will be cleared
        if (RESET == 1'b1) begin
            
            // Clearing every byte of the register in a loop
            for (i = 0; i < 8 ; i = i + 1) begin
                reg_array[i] <= #1 8'b00000000;
            end

        end

        // If write input is 1, right the IN value into the register[INADDRES]
        else if (WRITE == 1'b1) begin
            
            // Non-blocking assignment to the register
            reg_array[INADDRESS] <= #1 IN;

        end    
        
    end

endmodule

Lab3/cpu/cpu_tb.v
module cpu_tb;

    // OP-CODE list    
    `define ADD_    8'd0;
    `define SUB_    8'd1;
    `define AND_    8'd2;
    `define OR_     8'd3;
    `define J_      8'd4;
    `define BEQ_    8'd5;
    `define MOV_    8'd6;
    `define LOADI_  8'd7;

    reg [7:0]   OP_CODE;
    reg [7:0]   DEST_REG_IMM;
    reg [7:0]   SOURCE_REG_1;
    reg [7:0]   SOURCE_REG_2_IMM;


    wire [31:0] instruction;
    reg         CLK;
    wire [7:0]  pc;
    reg         RESET;


    cpu my_cpu(
        .PC(pc),
        .INSTRUCTION(instruction), 
        .CLK(CLK),
        .RESET(RESET)
    );

    
    // 32-bits wide 64 instructions (256 bytes)
    reg [31:0] instruction_memory [0:63];


    // CPU drives `pc`; testbench drives `instruction` from instruction_memory
    assign instruction = instruction_memory[pc[7:2]];

    initial begin
            
        // LOADI R1, 5
        OP_CODE = 8'd7;
        DEST_REG_IMM = 8'd1;
        SOURCE_REG_1 = 8'd0;
        SOURCE_REG_2_IMM  = 8'd5;

        instruction_memory[0] = {OP_CODE, DEST_REG_IMM, SOURCE_REG_1, SOURCE_REG_2_IMM};

        #2  // 2
        // LOADI R2, 2
        OP_CODE = 8'd7;
        DEST_REG_IMM = 8'd2;
        SOURCE_REG_1 = 8'd0;
        SOURCE_REG_2_IMM  = 8'd2;

        instruction_memory[1] = {OP_CODE, DEST_REG_IMM, SOURCE_REG_1, SOURCE_REG_2_IMM};

        #8  // 10
        // ADD R4, R1, R2
        OP_CODE = 8'd0;
        DEST_REG_IMM = 8'd4;
        SOURCE_REG_1 = 8'd1;
        SOURCE_REG_2_IMM  = 8'd2;

        instruction_memory[2] = {OP_CODE, DEST_REG_IMM, SOURCE_REG_1, SOURCE_REG_2_IMM};

        #8  // 18
        // LOADI R5, 10
        OP_CODE = 8'd7;
        DEST_REG_IMM = 8'd5;
        SOURCE_REG_1 = 8'd0;
        SOURCE_REG_2_IMM  = 8'd10;

        instruction_memory[3] = {OP_CODE, DEST_REG_IMM, SOURCE_REG_1, SOURCE_REG_2_IMM};

        #8  // 26
        // LOADI R6, 20
        OP_CODE = 8'd7;
        DEST_REG_IMM = 8'd6;
        SOURCE_REG_1 = 8'd0;
        SOURCE_REG_2_IMM  = 8'd20;

        instruction_memory[4] = {OP_CODE, DEST_REG_IMM, SOURCE_REG_1, SOURCE_REG_2_IMM};

        #8  // 34
        // SUB R7, R5, R6
        OP_CODE = 8'd1;
        DEST_REG_IMM = 8'd7;
        SOURCE_REG_1 = 8'd5;
        SOURCE_REG_2_IMM  = 8'd6;

        instruction_memory[5] = {OP_CODE, DEST_REG_IMM, SOURCE_REG_1, SOURCE_REG_2_IMM};

        #8  // 42
        // AND R3, R1, R2
        OP_CODE = 8'd2;
        DEST_REG_IMM = 8'd3;
        SOURCE_REG_1 = 8'd1;
        SOURCE_REG_2_IMM  = 8'd2;

        instruction_memory[6] = {OP_CODE, DEST_REG_IMM, SOURCE_REG_1, SOURCE_REG_2_IMM};

        #40  // 50-90: NOPs
        $finish;
    end

    initial begin
        CLK = 0;
        RESET = 1;
        #6;
        RESET = 0;
    end


    initial begin
        $dumpfile("cpu_wavedata.vcd");
        $dumpvars(0, cpu_tb);
        // Force the simulator to dump the memory array elements
        $dumpvars(0, my_cpu.my_reg_file.reg_array[0]);
        $dumpvars(0, my_cpu.my_reg_file.reg_array[1]);
        $dumpvars(0, my_cpu.my_reg_file.reg_array[2]);
        $dumpvars(0, my_cpu.my_reg_file.reg_array[3]);
        $dumpvars(0, my_cpu.my_reg_file.reg_array[4]);
        $dumpvars(0, my_cpu.my_reg_file.reg_array[5]);
        $dumpvars(0, my_cpu.my_reg_file.reg_array[6]);
        $dumpvars(0, my_cpu.my_reg_file.reg_array[7]);
    end

    initial begin
        $monitor("Time: %g, OP_CODE: %b, DEST_REG: %d SOURCE_1: %d, SOURCE_2_IMM: %d", $time, OP_CODE, DEST_REG_IMM, SOURCE_REG_1, SOURCE_REG_2_IMM);
    end

    always @(posedge CLK) begin
        $display("T=%0t PC=%0d R0=%0d R1=%0d R2=%0d R3=%0d R4=%0d R5=%0d R6=%0d R7=%0d",
            $time, pc,
            my_cpu.my_reg_file.reg_array[0],
            my_cpu.my_reg_file.reg_array[1],
            my_cpu.my_reg_file.reg_array[2],
            my_cpu.my_reg_file.reg_array[3],
            my_cpu.my_reg_file.reg_array[4],
            my_cpu.my_reg_file.reg_array[5],
            my_cpu.my_reg_file.reg_array[6],
            my_cpu.my_reg_file.reg_array[7]
        );
    end

    always begin
        #4
        CLK = ~CLK;
    end

endmodule

Lab3/cpu/cpu_wavedata.vcd
$date
	Fri Jun 05 23:11:30 2026
$end
$version
	Icarus Verilog
$end
$timescale
	1s
$end
$scope module cpu_tb $end
$var wire 32 ! instruction [31:0] $end
$var wire 8 " pc [7:0] $end
$var reg 1 # CLK $end
$var reg 8 $ DEST_REG_IMM [7:0] $end
$var reg 8 % OP_CODE [7:0] $end
$var reg 1 & RESET $end
$var reg 8 ' SOURCE_REG_1 [7:0] $end
$var reg 8 ( SOURCE_REG_2_IMM [7:0] $end
$scope module my_cpu $end
$var wire 1 # CLK $end
$var wire 32 ) INSTRUCTION [31:0] $end
$var wire 1 & RESET $end
$var wire 8 * in_val [7:0] $end
$var wire 8 + write_val [7:0] $end
$var wire 3 , write_reg [2:0] $end
$var wire 1 - write_enable $end
$var wire 8 . twos_comp_res [7:0] $end
$var wire 3 / select [2:0] $end
$var wire 8 0 regout2 [7:0] $end
$var wire 1 1 reg_or_imm $end
$var wire 1 2 reg2_or_twos_comp $end
$var wire 3 3 read_reg_2 [2:0] $end
$var wire 3 4 read_reg_1 [2:0] $end
$var wire 8 5 op_code [7:0] $end
$var wire 8 6 next_pc [7:0] $end
$var wire 8 7 mux1_res [7:0] $end
$var wire 8 8 immediate [7:0] $end
$var wire 8 9 alu_op_2 [7:0] $end
$var wire 8 : alu_op_1 [7:0] $end
$var reg 8 ; PC [7:0] $end
$scope module my_adder $end
$var wire 8 < PC_IN [7:0] $end
$var wire 8 = PC_OUT [7:0] $end
$upscope $end
$scope module my_alu $end
$var wire 8 > or_result [7:0] $end
$var wire 8 ? forward_result [7:0] $end
$var wire 8 @ and_result [7:0] $end
$var wire 8 A add_result [7:0] $end
$var wire 3 B SELECT [2:0] $end
$var wire 8 C RESULT [7:0] $end
$var wire 8 D DATA2 [7:0] $end
$var wire 8 E DATA1 [7:0] $end
$scope module myadd $end
$var wire 8 F DATA2 [7:0] $end
$var wire 8 G DATA1 [7:0] $end
$var reg 8 H RESULT [7:0] $end
$upscope $end
$scope module myand $end
$var wire 8 I DATA2 [7:0] $end
$var wire 8 J DATA1 [7:0] $end
$var reg 8 K RESULT [7:0] $end
$upscope $end
$scope module myforward $end
$var wire 8 L DATA2 [7:0] $end
$var reg 8 M RESULT [7:0] $end
$upscope $end
$scope module myor $end
$var wire 8 N DATA2 [7:0] $end
$var wire 8 O DATA1 [7:0] $end
$var reg 8 P RESULT [7:0] $end
$upscope $end
$upscope $end
$scope module my_control_unit $end
$var wire 8 Q OP_CODE [7:0] $end
$var reg 3 R ALU_OP [2:0] $end
$var reg 1 2 ORIG_OR_TWOS_COMP $end
$var reg 1 1 REG_OR_IMM $end
$var reg 1 - WRITE_ENABLE $end
$upscope $end
$scope module my_mux_1 $end
$var wire 1 2 SELECT $end
$var wire 8 S INPUT2 [7:0] $end
$var wire 8 T INPUT1 [7:0] $end
$var reg 8 U OUT_VAL [7:0] $end
$upscope $end
$scope module my_mux_2 $end
$var wire 8 V INPUT1 [7:0] $end
$var wire 8 W INPUT2 [7:0] $end
$var wire 1 1 SELECT $end
$var reg 8 X OUT_VAL [7:0] $end
$upscope $end
$scope module my_reg_file $end
$var wire 1 # CLK $end
$var wire 8 Y IN [7:0] $end
$var wire 3 Z INADDRESS [2:0] $end
$var wire 8 [ OUT1 [7:0] $end
$var wire 3 \ OUT1ADDRESS [2:0] $end
$var wire 8 ] OUT2 [7:0] $end
$var wire 3 ^ OUT2ADDRESS [2:0] $end
$var wire 1 & RESET $end
$var wire 1 - WRITE $end
$var integer 32 _ i [31:0] $end
$upscope $end
$scope module my_twos_complement $end
$var wire 8 ` IN_VAL [7:0] $end
$var wire 8 a OUT_VAL [7:0] $end
$upscope $end
$upscope $end
$upscope $end
$scope module cpu_tb $end
$scope module my_cpu $end
$scope module my_reg_file $end
$var reg 8 b \reg_array[0] [7:0] $end
$upscope $end
$upscope $end
$upscope $end
$scope module cpu_tb $end
$scope module my_cpu $end
$scope module my_reg_file $end
$var reg 8 c \reg_array[1] [7:0] $end
$upscope $end
$upscope $end
$upscope $end
$scope module cpu_tb $end
$scope module my_cpu $end
$scope module my_reg_file $end
$var reg 8 d \reg_array[2] [7:0] $end
$upscope $end
$upscope $end
$upscope $end
$scope module cpu_tb $end
$scope module my_cpu $end
$scope module my_reg_file $end
$var reg 8 e \reg_array[3] [7:0] $end
$upscope $end
$upscope $end
$upscope $end
$scope module cpu_tb $end
$scope module my_cpu $end
$scope module my_reg_file $end
$var reg 8 f \reg_array[4] [7:0] $end
$upscope $end
$upscope $end
$upscope $end
$scope module cpu_tb $end
$scope module my_cpu $end
$scope module my_reg_file $end
$var reg 8 g \reg_array[5] [7:0] $end
$upscope $end
$upscope $end
$upscope $end
$scope module cpu_tb $end
$scope module my_cpu $end
$scope module my_reg_file $end
$var reg 8 h \reg_array[6] [7:0] $end
$upscope $end
$upscope $end
$upscope $end
$scope module cpu_tb $end
$scope module my_cpu $end
$scope module my_reg_file $end
$var reg 8 i \reg_array[7] [7:0] $end
$upscope $end
$upscope $end
$upscope $end
$enddefinitions $end
$comment Show the parameter values. $end
$dumpall
$end
#0
$dumpvars
bx i
bx h
bx g
bx f
bx e
bx d
bx c
bx b
bx a
bx `
bx _
bx ^
bx ]
bx \
bx [
bx Z
bx Y
bx X
bx W
bx V
bx U
bx T
bx S
bx R
bx Q
bx P
bx O
bx N
bx M
bx L
bx K
bx J
bx I
bx H
bx G
bx F
bx E
bx D
bx C
bx B
bx A
bx @
bx ?
bx >
bx =
bx <
bx ;
bx :
bx 9
bx 8
bx 7
bx 6
bx 5
bx 4
bx 3
x2
x1
bx 0
bx /
bx .
x-
bx ,
bx +
bx *
bx )
b101 (
b0 '
1&
b111 %
b1 $
0#
bx "
bx !
$end
#2
b10 (
b10 $
#4
b1000 _
1#
#5
b0 i
b0 h
b0 g
b0 f
b0 e
b0 d
b0 c
b0 b
b101 8
b101 W
b111 5
b111 Q
b1 ,
b1 Z
b0 4
b0 \
b101 3
b101 ^
b111000000010000000000000101 !
b111000000010000000000000101 )
b0 "
b0 ;
b0 <
#6
b101 9
b101 D
b101 F
b101 I
b101 L
b101 N
b101 X
b0 /
b0 B
b0 R
1-
11
02
b100 6
b100 =
0&
#7
b101 +
b101 C
b101 Y
b101 >
b101 P
b0 @
b0 K
b101 ?
b101 M
b0 .
b0 S
b0 a
b0 7
b0 U
b0 V
b0 *
b0 `
b0 0
b0 T
b0 ]
b0 :
b0 E
b0 G
b0 J
b0 O
b0 [
#8
b101 A
b101 H
0#
#10
b1 '
b100 $
b0 %
#12
1#
#13
b101 c
b10 9
b10 D
b10 F
b10 I
b10 L
b10 N
b10 X
b10 8
b10 W
b10 ,
b10 Z
b10 3
b10 ^
b111000000100000000000000010 !
b111000000100000000000000010 )
b100 "
b100 ;
b100 <
#14
b10 +
b10 C
b10 Y
b10 >
b10 P
b10 ?
b10 M
b1000 6
b1000 =
#15
b10 A
b10 H
#16
0#
#18
b1010 (
b0 '
b101 $
b111 %
#20
1#
#21
b10 d
b0 5
b0 Q
b100 ,
b100 Z
b1 4
b1 \
b1000000000100000010 !
b1000000000100000010 )
b1000 "
b1000 ;
b1000 <
#22
b10 +
b10 C
b10 Y
b0 9
b0 D
b0 F
b0 I
b0 L
b0 N
b0 X
b1 /
b1 B
b1 R
1-
01
b1100 6
b1100 =
#23
b101 >
b101 P
b0 ?
b0 M
b10 9
b10 D
b10 F
b10 I
b10 L
b10 N
b10 X
b11111110 .
b11111110 S
b11111110 a
b10 7
b10 U
b10 V
b10 *
b10 `
b10 0
b10 T
b10 ]
b101 :
b101 E
b101 G
b101 J
b101 O
b101 [
#24
b111 +
b111 C
b111 Y
b111 >
b111 P
b10 ?
b10 M
b111 A
b111 H
0#
#26
b10100 (
b110 $
#28
1#
#29
b111 f
b1010 8
b1010 W
b111 5
b111 Q
b101 ,
b101 Z
b0 4
b0 \
b111000001010000000000001010 !
b111000001010000000000001010 )
b1100 "
b1100 ;
b1100 <
#30
b1010 9
b1010 D
b1010 F
b1010 I
b1010 L
b1010 N
b1010 X
b10 +
b10 C
b10 Y
11
b0 /
b0 B
b0 R
1-
b10000 6
b10000 =
#31
b1010 +
b1010 C
b1010 Y
b1010 >
b1010 P
b1010 ?
b1010 M
b0 :
b0 E
b0 G
b0 J
b0 O
b0 [
#32
b1010 A
b1010 H
0#
#34
b110 (
b101 '
b111 $
b1 %
#36
1#
#37
b1010 g
b10100 9
b10100 D
b10100 F
b10100 I
b10100 L
b10100 N
b10100 X
b10100 8
b10100 W
b110 ,
b110 Z
b100 3
b100 ^
b111000001100000000000010100 !
b111000001100000000000010100 )
b10000 "
b10000 ;
b10000 <
#38
b10100 +
b10100 C
b10100 Y
b10100 >
b10100 P
b10100 ?
b10100 M
b10100 6
b10100 =
#39
b10100 A
b10100 H
b11111001 .
b11111001 S
b11111001 a
b111 7
b111 U
b111 V
b111 *
b111 `
b111 0
b111 T
b111 ]
#40
0#
#42
b10 (
b1 '
b11 $
b10 %
#44
1#
#45
b10100 h
b110 9
b110 D
b110 F
b110 I
b110 L
b110 N
b110 X
b110 8
b110 W
b1 5
b1 Q
b111 ,
b111 Z
b101 4
b101 \
b110 3
b110 ^
b1000001110000010100000110 !
b1000001110000010100000110 )
b10100 "
b10100 ;
b10100 <
#46
b110 >
b110 P
b110 ?
b110 M
b11111001 7
b11111001 U
b11111001 V
b10100 +
b10100 C
b10100 Y
b11111001 9
b11111001 D
b11111001 F
b11111001 I
b11111001 L
b11111001 N
b11111001 X
12
b1 /
b1 B
b1 R
1-
01
b11000 6
b11000 =
#47
b11 +
b11 C
b11 Y
b1000 @
b1000 K
b11111011 >
b11111011 P
b11111001 ?
b11111001 M
b11 A
b11 H
b11101100 9
b11101100 D
b11101100 F
b11101100 I
b11101100 L
b11101100 N
b11101100 X
b11101100 7
b11101100 U
b11101100 V
b11101100 .
b11101100 S
b11101100 a
b1010 :
b1010 E
b1010 G
b1010 J
b1010 O
b1010 [
b10100 *
b10100 `
b10100 0
b10100 T
b10100 ]
#48
b11101110 >
b11101110 P
b11101100 ?
b11101100 M
0#
#49
b11110110 +
b11110110 C
b11110110 Y
b11110110 A
b11110110 H
#52
1#
#53
b11110110 i
b10 8
b10 W
b10 5
b10 Q
b11 ,
b11 Z
b1 4
b1 \
b10 3
b10 ^
b10000000110000000100000010 !
b10000000110000000100000010 )
b11000 "
b11000 ;
b11000 <
#54
b11101110 +
b11101110 C
b11101110 Y
b10100 9
b10100 D
b10100 F
b10100 I
b10100 L
b10100 N
b10100 X
b10100 7
b10100 U
b10100 V
b11 /
b11 B
b11 R
1-
02
b11100 6
b11100 =
#55
b10101 +
b10101 C
b10101 Y
b100 @
b100 K
b10101 >
b10101 P
b10100 ?
b10100 M
b10 9
b10 D
b10 F
b10 I
b10 L
b10 N
b10 X
b11111110 .
b11111110 S
b11111110 a
b10 7
b10 U
b10 V
b101 :
b101 E
b101 G
b101 J
b101 O
b101 [
b10 *
b10 `
b10 0
b10 T
b10 ]
#56
b111 +
b111 C
b111 Y
b111 >
b111 P
b0 @
b0 K
b10 ?
b10 M
b111 A
b111 H
0#
#60
1#
#61
b111 e
bx 8
bx W
bx 5
bx Q
bx ,
bx Z
bx 4
bx \
bx 3
bx ^
bx !
bx )
b11100 "
b11100 ;
b11100 <
#62
b10 +
b10 C
b10 Y
b0 /
b0 B
b0 R
0-
b100000 6
b100000 =
#63
bx 9
bx D
bx F
bx I
bx L
bx N
bx X
bx .
bx S
bx a
bx 7
bx U
bx V
bx :
bx E
bx G
bx J
bx O
bx [
bx *
bx `
bx 0
bx T
bx ]
#64
bx +
bx C
bx Y
bx ?
bx M
bx @
bx K
bx >
bx P
0#
#65
bx A
bx H
#68
1#
#69
b100000 "
b100000 ;
b100000 <
#70
b100100 6
b100100 =
#72
0#
#76
1#
#77
b100100 "
b100100 ;
b100100 <
#78
b101000 6
b101000 =
