Lab2/reg_file_tb/reg_file.v
module reg_file(IN, OUT1, OUT2, INADDRESS, OUT1ADDRESS, OUT2ADDRESS, WRITE, CLK, RESET);
    
                                                /*
    ============================================
                Port Declarations
    ============================================*/

    // Inputs
    
    // Input value to store  
    input [7:0] IN;   

    // Clock input, Write command, Reset commmand
    input CLK, WRITE, RESET;                            
    
    // Input register address to store
    // Output register adress 1 to output value 1
    // Output register adress 2 to output value 2
    input [2:0] INADDRESS, OUT1ADDRESS, OUT2ADDRESS;    
    
    // OUT1 and OUT2 is not declared as reg becuase continuous assignment doesn't allow that.
    // Therefore, they are kept as net values
    output wire [7:0] OUT1, OUT2;


                                                /*
    ============================================
          Internal Storage (8x8 register)
    ============================================*/

    // Declaring an array of 8, 8-byte arrays
    reg [7:0] reg_array [7:0];

    // Declaring integer i for the 'for' loop
    integer i;


                                                /*
    ============================================
            Reading Logic (Asynchronous)
    ============================================*/

    // Continuous assignment to OUT1 and OUT2
    // the values obtained from OUT1ADDRESS and OUT2ADDRESS
    assign #2 OUT1 = reg_array[OUT1ADDRESS];
    assign #2 OUT2 = reg_array[OUT2ADDRESS];


                                                /*
    ============================================
         Write and Reset Logic (Synchronous)
    ============================================*/

    // This 'always' block triggers when the clock is set to 1
    always @ (posedge CLK) begin
        
        // If reset input is 1, all of the registers will be cleared
        if (RESET == 1'b1) begin
            
            // Clearing every byte of the register in a loop
            for (i = 0; i < 8 ; i = i + 1) begin
                reg_array[i] <= #1 8'b00000000;
            end

        end

        // If write input is 1, right the IN value into the register[INADDRES]
        else if (WRITE == 1'b1) begin
            
            // Non-blocking assignment to the register
            reg_array[INADDRESS] <= #1 IN;

        end    
        
    end

endmodule

Lab2/reg_file_tb/reg_file_tb.v
// Computer Architecture CO2070 - Lab 02
// Design: Register File of Simple Processor
// Author: Kisaru Liyanage

module reg_file_tb;
    
    reg [7:0] WRITEDATA;
    reg [2:0] WRITEREG, READREG1, READREG2;
    reg CLK, RESET, WRITEENABLE; 
    wire [7:0] REGOUT1, REGOUT2;
    
    reg_file myregfile(WRITEDATA, REGOUT1, REGOUT2, WRITEREG, READREG1, READREG2, WRITEENABLE, CLK, RESET);
       
    initial
    begin
        CLK = 1'b1;
        
        // generate files needed to plot the waveform using GTKWave
        $dumpfile("reg_file_wavedata.vcd");
		$dumpvars(0, reg_file_tb);
        
        // assign values with time to input signals to see output 
        RESET = 1'b0;
        WRITEENABLE = 1'b0;
        
        #4  // 4
        RESET = 1'b1;
        READREG1 = 3'd0;
        READREG2 = 3'd4;
        
        #6  // 10
        RESET = 1'b0;
        
        #2  // 12
        WRITEREG = 3'd2;
        WRITEDATA = 8'd95;
        WRITEENABLE = 1'b1;
        
        #7  // 19
        WRITEENABLE = 1'b0;
        
        #1  // 20
        READREG1 = 3'd2;
        
        #7  // 27
        WRITEREG = 3'd1;
        WRITEDATA = 8'd28;
        WRITEENABLE = 1'b1;
        READREG1 = 3'd1;
        
        #8  // 35
        WRITEENABLE = 1'b0;
        
        #8  // 43
        WRITEREG = 3'd4;
        WRITEDATA = 8'd6;
        WRITEENABLE = 1'b1;
        
        #8  // 51
        WRITEDATA = 8'd15;
        WRITEENABLE = 1'b1;
        
        #10 // 61
        WRITEENABLE = 1'b0;
        
        #6  // 67
        WRITEREG = -3'd1;       // two's complement of 1 is -1, so the register is 7
        WRITEDATA = 8'd50;
        WRITEENABLE = 1'b1;
        
        #5  // 72
        WRITEENABLE = 1'b0;
        
        #10 // 82
        $finish;
    end
    
    // clock signal generation
    always
        #4 CLK = ~CLK;
        
    initial
    begin
        $monitor("Time %g, WRITEDATA = %d, REGOUT1 = %d, REGOUT2 = %d", $time, WRITEDATA, REGOUT1, REGOUT2);
    end

endmodule

Lab2/reg_file_tb/reg_file_wavedata.vcd
$date
	Tue May 26 08:49:34 2026
$end
$version
	Icarus Verilog
$end
$timescale
	1s
$end
$scope module reg_file_tb $end
$var wire 8 ! REGOUT2 [7:0] $end
$var wire 8 " REGOUT1 [7:0] $end
$var reg 1 # CLK $end
$var reg 3 $ READREG1 [2:0] $end
$var reg 3 % READREG2 [2:0] $end
$var reg 1 & RESET $end
$var reg 8 ' WRITEDATA [7:0] $end
$var reg 1 ( WRITEENABLE $end
$var reg 3 ) WRITEREG [2:0] $end
$scope module myregfile $end
$var wire 1 # CLK $end
$var wire 8 * IN [7:0] $end
$var wire 3 + INADDRESS [2:0] $end
$var wire 8 , OUT1 [7:0] $end
$var wire 3 - OUT1ADDRESS [2:0] $end
$var wire 8 . OUT2 [7:0] $end
$var wire 3 / OUT2ADDRESS [2:0] $end
$var wire 1 & RESET $end
$var wire 1 ( WRITE $end
$var integer 32 0 i [31:0] $end
$upscope $end
$upscope $end
$enddefinitions $end
$comment Show the parameter values. $end
$dumpall
$end
#0
$dumpvars
bx 0
bx /
bx .
bx -
bx ,
bx +
bx *
bx )
0(
bx '
0&
bx %
bx $
1#
bx "
bx !
$end
#4
0#
b100 %
b100 /
b0 $
b0 -
1&
#8
b1000 0
1#
#10
0&
#11
b0 !
b0 .
b0 "
b0 ,
#12
1(
b1011111 '
b1011111 *
b10 )
b10 +
0#
#16
1#
#19
0(
#20
b10 $
b10 -
0#
#22
b1011111 "
b1011111 ,
#24
1#
#27
b1 $
b1 -
1(
b11100 '
b11100 *
b1 )
b1 +
#28
0#
#29
b0 "
b0 ,
#32
1#
#35
b11100 "
b11100 ,
0(
#36
0#
#40
1#
#43
1(
b110 '
b110 *
b100 )
b100 +
#44
0#
#48
1#
#51
b110 !
b110 .
b1111 '
b1111 *
#52
0#
#56
1#
#59
b1111 !
b1111 .
#60
0#
#61
0(
#64
1#
#67
1(
b110010 '
b110010 *
b111 )
b111 +
#68
0#
#72
1#
0(
