Lab2/alu/alu.v
module alu(DATA1, DATA2, SELECT, RESULT);


                                                /*
    ============================================
                Port Declarations
    ============================================*/

    // 8-bit Data inputs
    input [7:0] DATA1, DATA2;
    
    // Selection input
    input [2:0] SELECT;

    // 8-bit output result
    output [7:0] RESULT;

    // 8-bit wires to hold the results of each operation
    wire [7:0] forward_result;
    wire [7:0] add_result;
    wire [7:0] and_result;
    wire [7:0] or_result;

                                                /*
    ============================================
                Module Instantiations
    ============================================*/
    
    // Forward module to forward DATA2 when SELECT is 000
    FORWARD myforward(
        .DATA2(DATA2), 
        .RESULT(forward_result)
    );

    // ADD module to add DATA1 and DATA2 when SELECT is 001
    ADD myadd(
        .DATA1(DATA1),
        .DATA2(DATA2),
        .RESULT(add_result)
    );
    
    // AND module to perform bitwise AND on DATA1 and DATA2 when SELECT is 010
    AND myand(
        .DATA1(DATA1),
        .DATA2(DATA2),
        .RESULT(and_result)
    );

    // OR module to perform bitwise OR on DATA1 and DATA2 when SELECT is 011
    OR myor(
        .DATA1(DATA1),
        .DATA2(DATA2),
        .RESULT(or_result)
    );

    // Continuous assignment to RESULT based on the value of SELECT
    assign RESULT = (SELECT == 3'b000) ? forward_result :
                    (SELECT == 3'b001) ? add_result :
                    (SELECT == 3'b010) ? and_result :
                    (SELECT == 3'b011) ? or_result :
                    8'b0;

endmodule


                                                /*
    ============================================
                Module Declarations
    ============================================*/

// Forward module to forward DATA2 when SELECT is 000
module FORWARD(DATA2, RESULT);

    input [7:0] DATA2;
    output reg [7:0] RESULT;
    
    always @ (DATA2)
    begin
        // Forwarding DATA2 to RESULT with a delay of 1 time unit
        #1 RESULT <= DATA2;
    end

endmodule



// ADD module to add DATA1 and DATA2 when SELECT is 001
module ADD(DATA1, DATA2, RESULT);

    input [7:0] DATA1, DATA2;
    output reg [7:0] RESULT;
    
    always @ (DATA1, DATA2)
    begin
        // Adding DATA1 and DATA2 and assigning the result to RESULT with a delay of 2 time units
        #2 RESULT <= DATA1 + DATA2;
    end

endmodule

// AND module to perform bitwise AND on DATA1 and DATA2 when SELECT is 010
module AND(DATA1, DATA2, RESULT);

    input [7:0] DATA1, DATA2;
    output reg [7:0] RESULT;
    
    always @ (DATA1, DATA2)
    begin
        // Performing bitwise AND on DATA1 and DATA2 and 
        // assigning the result to RESULT with a delay of 1 time unit
        #1 RESULT <= DATA1 & DATA2;
    end

endmodule


// OR module to perform bitwise OR on DATA1 and DATA2 when SELECT is 011
module OR(DATA1, DATA2, RESULT);

    input [7:0] DATA1, DATA2;
    output reg [7:0] RESULT;
    
    always @ (DATA1, DATA2)
    begin
        // Performing bitwise OR on DATA1 and DATA2 and
        // assigning the result to RESULT with a delay of 1 time unit  
        #1 RESULT <= DATA1 | DATA2;
    end

endmodule

Lab2/alu/alu_tb.v
module testbench;
    reg [7:0] OPERAND1, OPERAND2;
    reg [2:0] ALUOP;
    wire [7:0] ALURESULT;

    alu myalu(OPERAND1, OPERAND2, ALUOP, ALURESULT);

    initial
    begin

        // Forward 7 into result
        ALUOP = 3'b000;
        OPERAND2 = 8'b00000111;

        // Add: 5 + 3
        #5
        ALUOP = 3'b001;
        OPERAND1 = 8'b00000101;
        OPERAND2 = 8'b00000011;

        // Sub: 6 - 2
        // #5
        // ALUOP = 3'b001;
        // OPERAND1 = 8'b00000110;
        // OPERAND2 = 8'b00000010;
        

        // And: 101 & 001
        #5
        ALUOP = 3'b010;
        OPERAND1 = 8'b00000101;
        OPERAND2 = 8'b00000001;

        // Or: 1101 & 1011
        #5
        ALUOP = 3'b011;
        OPERAND1 = 8'b00001101;
        OPERAND2 = 8'b00001011;
    end


    initial
    begin
        
        $monitor("Time = %g, ALUOP = %b, OP1 = %b, OP2 = %b, RES = %b", $time, ALUOP, OPERAND1, OPERAND2, ALURESULT);
        #50 
        $finish;
    end


    initial
    begin
    
        $dumpfile("alu_wd.vcd");
        $dumpvars(0, testbench);
    
    end

endmodule

Lab2/alu/alu_wd.vcd
$date
	Tue May 26 00:17:12 2026
$end
$version
	Icarus Verilog
$end
$timescale
	1s
$end
$scope module testbench $end
$var wire 8 ! ALURESULT [7:0] $end
$var reg 3 " ALUOP [2:0] $end
$var reg 8 # OPERAND1 [7:0] $end
$var reg 8 $ OPERAND2 [7:0] $end
$scope module myalu $end
$var wire 8 % DATA1 [7:0] $end
$var wire 8 & DATA2 [7:0] $end
$var wire 3 ' SELECT [2:0] $end
$var wire 8 ( or_result [7:0] $end
$var wire 8 ) forward_result [7:0] $end
$var wire 8 * and_result [7:0] $end
$var wire 8 + add_result [7:0] $end
$var wire 8 , RESULT [7:0] $end
$scope module myadd $end
$var wire 8 - DATA1 [7:0] $end
$var wire 8 . DATA2 [7:0] $end
$var reg 8 / RESULT [7:0] $end
$upscope $end
$scope module myand $end
$var wire 8 0 DATA1 [7:0] $end
$var wire 8 1 DATA2 [7:0] $end
$var reg 8 2 RESULT [7:0] $end
$upscope $end
$scope module myforward $end
$var wire 8 3 DATA2 [7:0] $end
$var reg 8 4 RESULT [7:0] $end
$upscope $end
$scope module myor $end
$var wire 8 5 DATA1 [7:0] $end
$var wire 8 6 DATA2 [7:0] $end
$var reg 8 7 RESULT [7:0] $end
$upscope $end
$upscope $end
$upscope $end
$enddefinitions $end
$comment Show the parameter values. $end
$dumpall
$end
#0
$dumpvars
bx 7
b111 6
bx 5
bx 4
b111 3
bx 2
b111 1
bx 0
bx /
b111 .
bx -
bx ,
bx +
bx *
bx )
bx (
b0 '
b111 &
bx %
b111 $
bx #
b0 "
bx !
$end
#1
b111 !
b111 ,
bx111 (
bx111 7
b0xxx *
b0xxx 2
b111 )
b111 4
#5
bx !
bx ,
b11 $
b11 &
b11 .
b11 1
b11 3
b11 6
b101 #
b101 %
b101 -
b101 0
b101 5
b1 "
b1 '
#6
b11 )
b11 4
b1 *
b1 2
b111 (
b111 7
#7
b1000 !
b1000 ,
b1000 +
b1000 /
#10
b1 !
b1 ,
b1 $
b1 &
b1 .
b1 1
b1 3
b1 6
b10 "
b10 '
#11
b101 (
b101 7
b1 )
b1 4
#12
b110 +
b110 /
#15
b101 !
b101 ,
b1011 $
b1011 &
b1011 .
b1011 1
b1011 3
b1011 6
b1101 #
b1101 %
b1101 -
b1101 0
b1101 5
b11 "
b11 '
#16
b1111 !
b1111 ,
b1011 )
b1011 4
b1001 *
b1001 2
b1111 (
b1111 7
#17
b11000 +
b11000 /
