Lab2/v/alu-v.v
module alu(

    input [7:0] DATA1, DATA2,
    input [2:0] SELECT,
    output  [7:0] RESULT
);
wire [7:0] and_result, or_result, add_result, forward_result; // intermediate variables to hold the results of the and, or, add and forward modules



forward mux_forward(.DATA1(DATA1), .DATA2(DATA2), .RESULT(forward_result)); // athule thiyena ekkena thamai .data1, forward result is the intermediate variable, sort of a wire. connects the output of the forward module tot the input of the mux
my_add mux_add(.DATA1(DATA1), .DATA2(DATA2), .RESULT(add_result));
my_and mux_and(.DATA1(DATA1), .DATA2(DATA2), .RESULT(and_result));
my_or mux_or(.DATA1(DATA1), .DATA2(DATA2), .RESULT(or_result));

mux4to1 alu_mux(.DATA1(forward_result), .DATA2(add_result), .DATA3(and_result), .DATA4(or_result), .SELECT(SELECT), .RESULT(RESULT)); // connects the output of the forward module to the input of the mux, and the output of the mux to the output of the alu
endmodule


module my_and(
    input [7:0] DATA1, DATA2,
    output [7:0] RESULT
);
assign #1 RESULT = DATA1 & DATA2;
endmodule

module my_add(
    input [7:0] DATA1, DATA2,
    output  [7:0] RESULT
);
assign #2 RESULT = DATA1 + DATA2;
endmodule


module forward(
    input [7:0] DATA1, DATA2,
    output  [7:0] RESULT
);
assign #1 RESULT = DATA2;
endmodule

module my_or(
    input [7:0] DATA1, DATA2,
    output  [7:0] RESULT
);
assign #1 RESULT = DATA1 | DATA2;
endmodule


module mux4to1(
    input [7:0] DATA1, DATA2, DATA3, DATA4,
    input [2:0] SELECT,
    output reg [7:0] RESULT
);
    always @(*) begin
        case(SELECT)
            3'b000: RESULT = DATA1;
            3'b001: RESULT = DATA2;
            3'b010: RESULT = DATA3;
            3'b011: RESULT = DATA4;
            default RESULT = 8'bxxxxxxxx; // x is for low impedance
        endcase
    end
endmodule

Lab2/alu/group71_lab2_part1/group71_lab2_part1/alu_tb.v
module alu_tb;

    reg [7:0]  OPERAND1, OPERAND2;
    reg [2:0] ALUOP;
    wire [7:0] ALURESULT;

    alu myalu(OPERAND1, OPERAND2, ALUOP, ALURESULT);

    initial
    begin
        // generate files needed to plot the waveform using GTKWave
        $dumpfile("alu_wavedata.vcd");
        $dumpvars(0, alu_tb);

        // assign values with time to input signals to see output 

        
        // forward function
        OPERAND2 = 8'd10;
        ALUOP = 3'b000; 

        // add function
        #5
        ALUOP = 3'b001; 
        OPERAND1 = 8'd15;
        OPERAND2 = 8'd8;

        // and function
        #5
        ALUOP = 3'b010; 
        OPERAND1 = 8'd100;
        OPERAND2 = 8'd32;
        
        // or function
        #5
        ALUOP = 3'b011; 
        OPERAND1 = 8'd240;
        OPERAND2 = 8'd67;

        // Test with new operands on add function
        #5
        ALUOP = 3'b001;
        OPERAND1 = 8'd200;
        OPERAND2 = 8'd55;

        #5
        // Test invalid code
        ALUOP = 3'b100; // undefined function (expecting 8'bxxxxxxxx)

        #5
        $finish;
    end

    initial
    begin
        $monitor("Time: %g, OPERAND1: %b, OPERAND2: %b, ALUOP: %b, ALURESULT: %b", $time, OPERAND1, OPERAND2, ALUOP, ALURESULT);
    end
endmodule

Lab2/v/alu_wavedata.vcd
$date
	Tue May 26 22:36:03 2026
$end
$version
	Icarus Verilog
$end
$timescale
	1s
$end
$scope module alu_tb $end
$var wire 8 ! ALURESULT [7:0] $end
$var reg 3 " ALUOP [2:0] $end
$var reg 8 # OPERAND1 [7:0] $end
$var reg 8 $ OPERAND2 [7:0] $end
$scope module myalu $end
$var wire 8 % DATA1 [7:0] $end
$var wire 8 & DATA2 [7:0] $end
$var wire 3 ' SELECT [2:0] $end
$var wire 8 ( or_result [7:0] $end
$var wire 8 ) forward_result [7:0] $end
$var wire 8 * and_result [7:0] $end
$var wire 8 + add_result [7:0] $end
$var wire 8 , RESULT [7:0] $end
$scope module alu_mux $end
$var wire 3 - SELECT [2:0] $end
$var wire 8 . DATA4 [7:0] $end
$var wire 8 / DATA3 [7:0] $end
$var wire 8 0 DATA2 [7:0] $end
$var wire 8 1 DATA1 [7:0] $end
$var reg 8 2 RESULT [7:0] $end
$upscope $end
$scope module mux_add $end
$var wire 8 3 DATA1 [7:0] $end
$var wire 8 4 DATA2 [7:0] $end
$var wire 8 5 RESULT [7:0] $end
$upscope $end
$scope module mux_and $end
$var wire 8 6 DATA1 [7:0] $end
$var wire 8 7 DATA2 [7:0] $end
$var wire 8 8 RESULT [7:0] $end
$upscope $end
$scope module mux_forward $end
$var wire 8 9 DATA1 [7:0] $end
$var wire 8 : DATA2 [7:0] $end
$var wire 8 ; RESULT [7:0] $end
$upscope $end
$scope module mux_or $end
$var wire 8 < DATA1 [7:0] $end
$var wire 8 = DATA2 [7:0] $end
$var wire 8 > RESULT [7:0] $end
$upscope $end
$upscope $end
$upscope $end
$enddefinitions $end
$comment Show the parameter values. $end
$dumpall
$end
#0
$dumpvars
bx >
b1010 =
bx <
bx ;
b1010 :
bx 9
bx 8
b1010 7
bx 6
bx 5
b1010 4
bx 3
bx 2
bx 1
bx 0
bx /
bx .
b0 -
bx ,
bx +
bx *
bx )
bx (
b0 '
b1010 &
bx %
b1010 $
bx #
b0 "
bx !
$end
#1
b1010 !
b1010 ,
b1010 2
bx1x1x (
bx1x1x .
bx1x1x >
b0x0x0 *
b0x0x0 /
b0x0x0 8
b1010 )
b1010 1
b1010 ;
#5
bx !
bx ,
bx 2
b1000 $
b1000 &
b1000 4
b1000 7
b1000 :
b1000 =
b1111 #
b1111 %
b1111 3
b1111 6
b1111 9
b1111 <
b1 "
b1 '
b1 -
#6
b1000 *
b1000 /
b1000 8
b1111 (
b1111 .
b1111 >
b1000 )
b1000 1
b1000 ;
#7
b10111 !
b10111 ,
b10111 2
b10111 +
b10111 0
b10111 5
#10
b1000 !
b1000 ,
b1000 2
b100000 $
b100000 &
b100000 4
b100000 7
b100000 :
b100000 =
b1100100 #
b1100100 %
b1100100 3
b1100100 6
b1100100 9
b1100100 <
b10 "
b10 '
b10 -
#11
b100000 !
b100000 ,
b100000 2
b100000 *
b100000 /
b100000 8
b1100100 (
b1100100 .
b1100100 >
b100000 )
b100000 1
b100000 ;
#12
b10000100 +
b10000100 0
b10000100 5
#15
b1100100 !
b1100100 ,
b1100100 2
b1000011 $
b1000011 &
b1000011 4
b1000011 7
b1000011 :
b1000011 =
b11110000 #
b11110000 %
b11110000 3
b11110000 6
b11110000 9
b11110000 <
b11 "
b11 '
b11 -
#16
b11110011 !
b11110011 ,
b11110011 2
b1000000 *
b1000000 /
b1000000 8
b11110011 (
b11110011 .
b11110011 >
b1000011 )
b1000011 1
b1000011 ;
#17
b110011 +
b110011 0
b110011 5
#20
b110011 !
b110011 ,
b110011 2
b110111 $
b110111 &
b110111 4
b110111 7
b110111 :
b110111 =
b11001000 #
b11001000 %
b11001000 3
b11001000 6
b11001000 9
b11001000 <
b1 "
b1 '
b1 -
#21
b0 *
b0 /
b0 8
b11111111 (
b11111111 .
b11111111 >
b110111 )
b110111 1
b110111 ;
#22
b11111111 !
b11111111 ,
b11111111 2
b11111111 +
b11111111 0
b11111111 5
#25
bx !
bx ,
bx 2
b100 "
b100 '
b100 -
